random_flavorpack/__init__.py
random_flavorpack/apps.py
random_flavorpack/models.py
random_flavorpack/random_flavorpack_settings.py
random_flavorpack/utils.py
random_flavorpack/wsgi.py
random_flavorpack/api/__init__.py
random_flavorpack/api/routers.py
random_flavorpack/api/serializers.py
random_flavorpack/api/urls.py
random_flavorpack/api/viewsets.py
random_flavorpack/generators/__init__.py
random_flavorpack/generators/common.py
random_flavorpack/generators/random.py
random_flavorpack/management/__init__.py
random_flavorpack/management/commands/__init__.py
random_flavorpack/management/commands/load_random_flavorpack_auth.py
random_flavorpack/management/commands/load_test_random_pools.py
random_flavorpack/tests/__init__.py
random_flavorpack/tests/randomized_region_tests.py
random_flavorpack/tests/settings.py
random_flavorpack/tests/urls.py
random_flavorpack-3.0.2.dist-info/LICENSE.md
random_flavorpack-3.0.2.dist-info/METADATA
random_flavorpack-3.0.2.dist-info/WHEEL
random_flavorpack-3.0.2.dist-info/top_level.txt
random_flavorpack-3.0.2.dist-info/RECORD
