Metadata-Version: 2.1
Name: random-flavorpack
Version: 3.0.2
Summary: Randomized Number Flavorpack Plugin for SerialBox
Home-page: https://gitlab.com/serial-lab/random-flavorpack
Author: SerialLab Corp
Author-email: slab@serial-lab.com
License: GPLv3
Keywords: seriallab,quartet,randomized,numbers,serialbox,level-4 quartet
Platform: UNKNOWN
Classifier: Development Status :: 5 - Production/Stable
Classifier: Environment :: Web Environment
Classifier: Framework :: Django
Classifier: Intended Audience :: Developers
Classifier: License :: OSI Approved :: GNU General Public License v3 (GPLv3)
Classifier: Natural Language :: English
Classifier: Programming Language :: Python :: 3.10
Classifier: Programming Language :: Python :: 3.11
Classifier: Programming Language :: Python :: 3.12
